INSTALL.txt
LICENSE.txt
MANIFEST.in
README.md
flickr-rsync.ini
setup.cfg
setup.py
flickr_rsync/__init__.py
flickr_rsync/__main__.py
flickr_rsync/_version.py
flickr_rsync/config.py
flickr_rsync/csv_walker.py
flickr_rsync/enumerate_peek.py
flickr_rsync/fake_storage.py
flickr_rsync/file_info.py
flickr_rsync/flickr_storage.py
flickr_rsync/folder_info.py
flickr_rsync/local_storage.py
flickr_rsync/resiliently.py
flickr_rsync/root_folder_info.py
flickr_rsync/rx_sync.py
flickr_rsync/storage.py
flickr_rsync/sync.py
flickr_rsync/throttle.py
flickr_rsync/tree_walker.py
flickr_rsync/walker.py
flickr_rsync.egg-info/PKG-INFO
flickr_rsync.egg-info/SOURCES.txt
flickr_rsync.egg-info/dependency_links.txt
flickr_rsync.egg-info/entry_points.txt
flickr_rsync.egg-info/requires.txt
flickr_rsync.egg-info/top_level.txt
flickr_rsync.egg-info/zip-safe