Metadata-Version: 1.1
Name: flickr-rsync
Version: 1.0.5
Summary: A python script to manage synchronising a local directory of photos with flickr based on an rsync interaction pattern
Home-page: http://www.phdesign.com.au/flickr-rsync
Author: Paul Heasley
Author-email: paul@phdesign.com.au
License: MIT
Download-URL: https://github.com/phdesign/flickr-rsync/archive/v1.0.5.tar.gz
Keywords: flickr,sync,rsync
Platform: UNKNOWN
